error_grids.py
error_grids-0.1.0.dist-info/LICENSE
error_grids-0.1.0.dist-info/METADATA
error_grids-0.1.0.dist-info/WHEEL
error_grids-0.1.0.dist-info/top_level.txt
error_grids-0.1.0.dist-info/RECORD
