Metadata-Version: 2.1
Name: error-grids
Version: 0.1.0
Summary: Python Implementation of Clarke and Parkes Error Grids for Blood Glucose Accuracy Analysis
Home-page: https://github.com/kriventsov/Clarke-and-Parkes-Error-Grids
Author: Your Name
Author-email: your@email.com
License: UNKNOWN
Platform: UNKNOWN
Classifier: Programming Language :: Python :: 3
Classifier: License :: OSI Approved :: MIT License
Classifier: Operating System :: OS Independent
License-File: LICENSE
